Workbook

Sheet 01_月額サマリー
A1: 月額ランニングコスト（受講者数別）
A2: 受講者数（3行目の黄色セル）を変えると全体が再計算されます。金額は税抜です。
A4: 項目 | B4: ケース1 | C4: ケース2 | D4: ケース3 | E4: 算出方法
A5: 月間の受講者数 | B5: 50 | C5: 100 | D5: 300 | E5: 想定される規模。年間では600名／1,200名／3,600名
A7: A. 固定費
A8: 保守・運用サービス（弊社） | B8: =02_単価と前提!$B$15 -> 80000 | C8: =02_単価と前提!$B$15 -> 80000 | D8: =02_単価と前提!$B$15 -> 80000 | E8: 定額。監視・障害対応・軽微改修・問い合わせ一次対応
A9: インフラ・SaaS 固定費 | B9: =02_単価と前提!$B$24-02_単価と前提!$B$15 -> 24200 | C9: =02_単価と前提!$B$24-02_単価と前提!$B$15 -> 24200 | D9: =02_単価と前提!$B$24-02_単価と前提!$B$15 -> 24200 | E9: サーバー、DB、キャッシュ、監視、バックアップ、ドメイン等
A10: 固定費 小計 | B10: =SUM(B8:B9) -> 104200 | C10: =SUM(C8:C9) -> 104200 | D10: =SUM(D8:D9) -> 104200
A12: B. 変動費（受講者数に比例）
A13: 動画配信（CDN転送） | B13: =ROUND(MAX(0,$B$5*02_単価と前提!$B$6-02_単価と前提!$B$11)*02_単価と前提!$B$28,0) -> 0 | C13: =ROUND(MAX(0,$C$5*02_単価と前提!$B$6-02_単価と前提!$B$11)*02_単価と前提!$B$28,0) -> 0 | D13: =ROUND(MAX(0,$D$5*02_単価と前提!$B$6-02_単価と前提!$B$11)*02_単価と前提!$B$28,0) -> 445 | E13: 受講者数×3.5GB。月1TBの無料枠を差し引いて課金
A14: オブジェクトストレージ | B14: =ROUND((50+$B$5*0.02)*02_単価と前提!$B$29,0) -> 191 | C14: =ROUND((50+$C$5*0.02)*02_単価と前提!$B$29,0) -> 195 | D14: =ROUND((50+$D$5*0.02)*02_単価と前提!$B$29,0) -> 210 | E14: 教材動画 約50GB＋本人確認画像（1人あたり約20MB）
A15: 顔照合API | B15: =ROUND($B$5*02_単価と前提!$B$7*02_単価と前提!$B$30,0) -> 165 | C15: =ROUND($C$5*02_単価と前提!$B$7*02_単価と前提!$B$30,0) -> 330 | D15: =ROUND($D$5*02_単価と前提!$B$7*02_単価と前提!$B$30,0) -> 990 | E15: 受講者数×22回×単価
A16: ライブネス判定 | B16: =ROUND($B$5*02_単価と前提!$B$8*02_単価と前提!$B$31,0) -> 146 | C16: =ROUND($C$5*02_単価と前提!$B$8*02_単価と前提!$B$31,0) -> 293 | D16: =ROUND($D$5*02_単価と前提!$B$8*02_単価と前提!$B$31,0) -> 878 | E16: 受講者数×1回×単価
A17: メール送信 | B17: =ROUND($B$5*5*02_単価と前提!$B$32,0) -> 5 | C17: =ROUND($C$5*5*02_単価と前提!$B$32,0) -> 10 | D17: =ROUND($D$5*5*02_単価と前提!$B$32,0) -> 30 | E17: 受講者数×5通×単価
A18: 変動費 小計 | B18: =SUM(B13:B17) -> 507 | C18: =SUM(C13:C17) -> 828 | D18: =SUM(D13:D17) -> 2553
A20: 月額ランニングコスト 合計（税抜） | B20: =B10+B18 -> 104707 | C20: =C10+C18 -> 105028 | D20: =D10+D18 -> 106753 | E20: 決済手数料を除く
A21: うち 受講者1名あたり | B21: =ROUND(B20/B5,0) -> 2094 | C21: =ROUND(C20/C5,0) -> 1050 | D21: =ROUND(D20/D5,0) -> 356 | E21: 受講者が増えるほど1名あたりの負担は下がります
A23: C. 売上連動費（参考・上記合計には含みません）
A24: 決済手数料 | B24: =ROUND($B$5*02_単価と前提!$B$9*02_単価と前提!$B$10,0) -> 18000 | C24: =ROUND($C$5*02_単価と前提!$B$9*02_単価と前提!$B$10,0) -> 36000 | D24: =ROUND($D$5*02_単価と前提!$B$9*02_単価と前提!$B$10,0) -> 108000 | E24: 受講者数×受講料10,000円×3.6%。売上から支払う費用です
A25: （参考）月間の想定売上 | B25: =$B$5*02_単価と前提!$B$9 -> 500000 | C25: =$C$5*02_単価と前提!$B$9 -> 1000000 | D25: =$D$5*02_単価と前提!$B$9 -> 3000000 | E25: 受講料10,000円で試算
A26: （参考）売上－ランニング費用 | B26: =B25-B20-B24 -> 377293 | C26: =C25-C20-C24 -> 858972 | D26: =D25-D20-D24 -> 2785247 | E26: 教材の償却前。ここが黒字になる受講者数が損益分岐です
A28: ■ 読み方
A29: ・固定費は受講者が0名でも発生します。月額約10万円が事業を維持する最低ラインです。
A30: ・変動費は受講者数に比例しますが、規模の割に小さい金額です。CDNの無料枠が効いています。
A31: ・したがって、この事業の損益は「固定費を何名で割るか」でほぼ決まります。
A32: ・受講料10,000円なら、月11〜12名で固定費を回収できる計算になります。

Sheet 02_単価と前提
A1: ランニングコストの単価と前提
A2: 黄色のセルが入力欄です。ここを変えると全シートが自動で再計算されます。金額は2026年9月時点の公開情報に基づく想定値です。
A4: 共通の前提
A5: 為替レート | B5: 150 | C5: AWS等のドル建て費用の換算に使用します
A6: 1受講あたりの動画転送量 | B6: 3.5 | C6: 学科4.5時間・720p（約1.5Mbps）＋再視聴分を見込んだ値
A7: 1受講あたりの顔照合回数 | B7: 22 | C7: 受講開始時＋受講中のランダム照合（1時間あたり3回）
A8: 1受講あたりのライブネス判定 | B8: 1 | C8: アカウント登録時の1回のみ
A9: 受講料（決済手数料の算出用） | B9: 10000 | C9: プランAの想定単価。売上連動費の試算に使用します
A10: 決済手数料率 | B10: 0.036 | C10: クレジットカード決済の一般的な料率
A11: CDN無料枠 | B11: 1024 | C11: CloudFrontの永年無料枠。月1TBまでインターネットへの転送が無料
A13: A. 固定費（受講者数に関係なく毎月発生）
A14: 項目 | B14: 月額 | C14: 内容 | D14: 提供元 | E14: 備考
A15: 保守・運用サービス（弊社） | B15: 80000 | C15: 監視、障害対応、軽微な改修、受講者からの問い合わせ一次対応 | D15: 株式会社スペリオル | E15: 聖建様よりご提示の金額
A16: アプリケーションサーバー | B16: 4500 | C16: EC2 t3.medium 相当（2vCPU／4GB）。Laravel／Nginx／PHP-FPM | D16: AWS | E16: Xserver VPSなら約4,000〜8,000円
A17: データベース | B17: 5500 | C17: RDS PostgreSQL db.t3.small 相当。自動バックアップとPITRを含む | D17: AWS | E17: 自前構築なら安いが復旧責任を負う
A18: キャッシュ・キュー | B18: 2000 | C18: ElastiCache Redis cache.t3.micro 相当。多重視聴の排他制御に使用 | D18: AWS | E18: VPS同居なら0円
A19: ロードバランサ・固定IP・その他 | B19: 3500 | C19: ALB、Elastic IP、NAT等 | D19: AWS
A20: ドメイン・SSL | B20: 200 | C20: 年間約2,000円を月割。SSLはACMで無料 | D20: AWS／レジストラ
A21: 監視・エラー追跡 | B21: 3000 | C21: Sentry等。障害と不正兆候の検知 | D21: 外部SaaS | E21: 無料枠から開始すれば当面0円
A22: バックアップ保管 | B22: 500 | C22: S3標準〜低頻度アクセス。DBスナップショットと記録の長期保存 | D22: AWS | E22: 3年保存義務に対応
A23: アバター・音声合成サービス | B23: 5000 | C23: 教材を継続制作する期間のみ。制作を終えれば解約可能 | D23: 外部SaaS | E23: 初年度のみ想定
A24: 固定費 小計 | B24: =SUM(B15:B23) -> 104200
A26: B. 変動費の単価（受講者数に比例）
A27: 項目 | B27: 単価 | C27: 単位 | D27: 算出根拠 | E27: 備考
A28: 動画配信（CDN転送） | B28: =0.114*$B$5 -> 17.1 | C28: 円／GB | D28: CloudFront 日本 $0.114／GB | E28: 月1TBまで無料枠あり
A29: オブジェクトストレージ | B29: =0.025*$B$5 -> 3.75 | C29: 円／GB／月 | D29: S3標準 $0.025／GB／月 | E29: 動画58時間分＋本人確認画像
A30: 顔照合API | B30: =0.001*$B$5 -> 0.15 | C30: 円／回 | D30: Rekognition CompareFaces $0.001／画像 | E30: 受講者1人あたり22回
A31: ライブネス判定 | B31: =0.0195*$B$5 -> 2.925 | C31: 円／回 | D31: Rekognition Face Liveness $0.0195／回 | E31: 受講者1人あたり1回
A32: メール送信 | B32: 0.02 | C32: 円／通 | D32: SES等。1人あたり約5通 | E32: ほぼ無視できる水準
A34: ■ この明細の考え方
A35: ・固定費は、受講者が0人でも毎月発生します。事業の損益分岐を決めるのはこの金額です。
A36: ・変動費は受講者数に比例します。受講料に含めて回収する性質の費用です。
A37: ・決済手数料は売上に比例するため、別枠（シート01の C欄）で表示しています。
A39: ■ 出典と注意
A40: ・AWSの単価は2026年9月時点の公開情報に基づく想定です。実際の請求はリージョン・構成・使用量で変動します。
A41: ・CloudFrontには月1TBの永年無料枠があります。立ち上げ期の配信費はほぼ発生しません。
A42: ・正式なご提示の前に、実際の構成でAWS Pricing Calculatorによる試算をお勧めします。

Sheet 03_サーバー構成の比較
A1: サーバー構成の比較
A2: 配信システム基本設計書 1.1 が求める前提（PHP 8.3／Laravel／PostgreSQL／Redis／HLS／FFmpeg／常駐ワーカー）に照らした評価です。
A4: 評価項目 | B4: エックスサーバー（共用） | C4: Xserver VPS | D4: AWS（推奨）
A5: 月額の目安 | B5: 1,100円程度 | C5: 4,000〜10,000円程度 （2026年9月1日 改定後・要確認） | D5: 15,000〜20,000円程度
A6: PostgreSQL | B6: ✕ 非対応（MySQL系のみ） | C6: ○ 自分で導入 | D6: ◎ RDSマネージド
A7: Redis | B7: ✕ 使えない | C7: ○ 自分で導入 | D7: ◎ ElastiCache
A8: FFmpegでの動画変換 | B8: ✕ 実行制限で不可 | C8: ○ 可能 | D8: ◎ 可能
A9: 常駐ワーカー（Queue／Scheduler） | B9: ✕ 持てない | C9: ○ 可能 | D9: ◎ 可能
A10: HLS配信・署名付きURL・CDN | B10: ✕ 実質不可 | C10: △ 別途CDNが必要 | D10: ◎ S3＋CloudFront
A11: DBの自動バックアップ・PITR | B11: ✕ | C11: △ 自分で仕組みを作る | D11: ◎ 標準機能
A12: 障害からの復旧 | B12: ✕ | C12: △ 手作業。復旧時間が読めない | D12: ◎ スナップショットから復元
A13: 受講者増への対応 | B13: ✕ | C13: △ 手作業でプラン変更 | D13: ◎ スケールアウト可能
A14: 顔照合API（Rekognition）との親和性 | B14: ― | C14: △ 外部連携 | D14: ◎ 同一基盤・国内リージョン
A15: 運用にかかる手間 | B15: ― | C15: 多い | D15: 少ない
A16: 総合評価 | B16: ✕ 採用不可 | C16: △ 条件付きで可 | D16: ◎ 推奨
A18: ■ 結論
A19: エックスサーバーの共用レンタルサーバーでは、この設計は動きません。
A20: PostgreSQLもRedisも使えず、FFmpegでの動画変換も常駐ワーカーも持てません。設計書の前提を満たしません。
A22: Xserver VPS なら技術的には構築できます。root権限があるため、必要なものは自分で導入できます。
A23: ただし、バックアップ・冗長化・監視・スケールをすべて自分で作ることになります。
A25: 弊社はAWSを推奨します。理由は費用ではなく、記録を失わないためです。
A26: 本人確認と受講の記録は3年以上の保存義務があります。この記録を失うことは、事業の根幹である
A27: 「証明できること」が崩れることを意味します。RDSの自動バックアップとPITRは、この事業では
A28: 贅沢品ではなく必需品です。月額の差は1万円程度で、その保険料としては安いと考えます。
A30: 顔照合にAWS Rekognitionを使うため、同じ基盤に載せるほうが構成が単純になり、
A31: 個人データの国外移転の問題も生じにくくなります。
A33: ■ 費用を抑える方法
... A37: ・CloudFrontの無料枠（月1TB）があるため、立ち上げ期の配信費はほぼ発生しません。

Sheet 04_契約の分け方
A1: 月額8万円に、サーバー費を含めるべきか
A3: 結論：含めないでください。実費は別途とすべきです。
B5: 含める場合 | C5: 別途にする場合（推奨）
A6: 受講者が増えたとき | B6: 転送量・顔照合・ストレージが増え、8万円では赤字になります。事業が成功するほど御社が損をします。 | C6: 実費が受講者数に応じて増えるだけです。受講料で回収できます。
A7: 聖建様側の見え方 | B7: 何にいくらかかっているか分かりません。原価管理ができません。 | C7: 実費が明細で見えます。受講料の設定根拠になります。
A8: 為替が動いたとき | B8: ドル建て費用が上がっても御社が吸収することになります。 | C8: 実費として自動的に反映されます。
A9: 契約が終わるとき | B9: サーバーの契約主体が御社のため、引き継ぎが煩雑になります。 | C9: 聖建様名義であれば、そのまま継続できます。
A10: 値上げ交渉 | B10: 毎年「上げてください」と言う必要があります。 | C10: 不要です。
A12: ■ 推奨する契約の形
A14: ① 月額 80,000円（税抜）＝ 保守・運用サービス
A15: 監視、障害対応、軽微な改修、受講者からの問い合わせ一次対応、月次レポート。
A16: 人的サービスの対価であり、受講者数に左右されません。
A18: ② インフラ実費 ＝ 聖建様名義でAWSと直接ご契約（推奨）
A19: 御社は運用代行のみを行います。立替えが発生せず、費用が透明になります。
A20: 聖建様側でアカウント管理が難しい場合は、弊社が代行契約し、
A21: 実費＋事務手数料10%でご請求する形も可能です。
A23: ③ 従量サービス（顔照合・ライブネス・決済）
A24: ②と同じ扱いとします。受講者数に比例するため、定額に含めるべきではありません。
A26: ■ ご提示のしかた
A27: 「月額8万円は保守・運用の費用です。サーバーとAPIの実費は、受講者数で変わるため別途とさせてください。
... A32: この説明なら、値切りではなく合理性の話として受け取っていただけます。
