Workbook

Sheet 01_概算サマリー
A1: 特別教育 eラーニング事業 全体概算
A2: 株式会社聖建 御中 ／ 株式会社スペリオル ／ 2026年8月30日時点の概算
B4: 項目 | C4: 概算(下限) | D4: 概算(上限) | E4: 備考
B5: 教材制作費（選択した科目の合計） | C5: =03_教材制作費!H31 -> 5035000 | D5: =03_教材制作費!H31 -> 5035000 | E5: シート03で科目を選択すると自動で反映されます。上限・下限は同額（単価は1本）
B6: システム初期費用 フェーズ1 | C6: =04_システム費用!C15 -> 2200000 | D6: =04_システム費用!D15 -> 3800000 | E6: 受講者ポータル、本人確認、動画配信、テスト、修了証。まずここから
B7: システム初期費用 フェーズ2 | C7: =04_システム費用!C16 -> 1200000 | D7: =04_システム費用!D16 -> 2100000 | E7: 企業管理ポータル、決済、運営管理、記録保存。運用開始後に追加
B8: 初期投資 合計 | C8: =SUM(C5:C7) -> 8435000 | D8: =SUM(D5:D7) -> 10935000
B9: うち フェーズ1 までで着手する場合 | C9: =C5+C6 -> 7235000 | D9: =D5+D6 -> 8835000 | E9: 教材とフェーズ1のみ。まずこの範囲でのご検討を推奨します
B11: 月額運用費（固定分） | C11: =04_システム費用!C25 -> 50000 | D11: =04_システム費用!D25 -> 90000 | E11: 別途、本人確認APIと動画配信の従量課金が発生します
B14: 選択中の科目数 | C14: =03_教材制作費!A31 -> 3 | D14: 科目 | E14: シート03のA列で選択します
B15: 選択中の学科時間 合計 | C15: =03_教材制作費!C31 -> 14.5 | E15: 制作する動画の総尺の設計基準になります
B18: ■ このシートの使い方
B19: ・シート03「教材制作費」のA列に 1 を入れると、その科目が集計に入ります。初期状態では足場・フルハーネス・テールゲートリフターの3科目を選択しています。
B20: ・単価（黄色のセル）を変更すると、このサマリーまで自動で再計算されます。
B21: ・緑色の数字は他シートからの参照、青色の数字は入力値、黒色は計算結果です。
B23: ■ 重要：この金額は概算です
B24: ・単価は同種案件の一般的な相場に基づく想定値です。正式なお見積りは要件確定後に別途ご提示します。
B25: ・シート05に、金額の前提と責任の分担範囲を記載しています。必ずあわせてご確認ください。

Sheet 02_科目マスタ
A1: 特別教育 科目別 法定時間マスタ
A2: 出典：安全衛生特別教育規程（昭和47年労働省告示第92号）ほか。学科時間が、eラーニング動画の尺を設計する基準になります。
A4: 業務の名称 | B4: 学科 (時間) | C4: 実技 (時間) | D4: 合計 (時間) | E4: eラーニング適性 | F4: 確認状況・備考
A5: 足場の組立て等の業務 | B5: 6 | C5: 0 | D5: =B5+C5 -> 6 | E5: ◎ 学科のみで完結 | F5: 実技の定めなし。オンラインで修了まで完結できる有力候補
A6: 粉じん作業に係る業務 | B6: 4.5 | C6: 0 | D6: =B6+C6 -> 4.5 | E6: ◎ 学科のみで完結 | F6: じん肺法・粉じん障害防止規則関連。実技の定めなし
A7: 石綿等が使用されている建築物等の解体等の業務 | B7: 4.5 | C7: 0 | D7: =B7+C7 -> 4.5 | E7: ◎ 学科のみで完結 | F7: 石綿障害予防規則。解体・改修需要が継続的にある
A8: 酸素欠乏・硫化水素危険作業（第2種） | B8: 5.5 | C8: 0 | D8: =B8+C8 -> 5.5 | E8: ◎ 学科のみで完結 | F8: 酸素欠乏危険作業特別教育規程。第1種は科目構成が異なるため要原典確認
A9: フルハーネス型墜落制止用器具を用いて行う作業 | B9: 4.5 | C9: 1.5 | D9: =B9+C9 -> 6 | E9: ○ 学科のみ提供 | F9: 実技1.5時間は受講者の所属事業者が実施。Web講座の標準的な提供形態
A10: テールゲートリフターの操作の業務 | B10: 4 | C10: 2 | D10: =B10+C10 -> 6 | E10: ○ 学科のみ提供 | F10: 2024年2月1日より義務化。新規需要が最も大きい科目
A11: 自由研削といしの取替え等の業務 | B11: 4 | C11: 3 | D11: =B11+C11 -> 7 | E11: ○ 学科のみ提供 | F11: 製造業・建設業ともに対象者が多い
A12: 低圧電気取扱業務（開閉器の操作のみ） | B12: 7 | C12: 1 | D12: =B12+C12 -> 8 | E12: ○ 学科のみ提供 | F12: 実技は1時間以上。学科が7時間と長く、制作費は上振れする
A13: 低圧電気取扱業務（充電電路の敷設等） | B13: 7 | C13: 7 | D13: =B13+C13 -> 14 | E13: △ 学科のみ提供 | F13: 実技7時間以上。実技負担が大きく受講者側のハードルが高い
A14: 高所作業車の運転（作業床の高さ10m未満） | B14: 6 | C14: 3 | D14: =B14+C14 -> 9 | E14: ○ 学科のみ提供 | F14: 実技3時間は実機が必要
A15: 玉掛けの業務（つり上げ荷重1トン未満） | B15: 5 | C15: 4 | D15: =B15+C15 -> 9 | E15: ○ 学科のみ提供 | F15: 実技4時間は実機が必要
A16: 小型車両系建設機械の運転（機体重量3トン未満） | B16: 7 | C16: 6 | D16: =B16+C16 -> 13 | E16: △ 学科のみ提供 | F16: 実技6時間。整地・運搬・積込み用および掘削用
... A18: アーク溶接等の業務 | B18: 11 | C18: 10 | D18: =B18+C18 -> 21 | E18: △ 学科のみ提供 | F18: 学科11時間・実技10時間と最大級。制作費が最も高くなる
A20: 参考：特別教育以外の教育（同じ仕組みで配信できます）
A21: 【参考】職長・安全衛生責任者教育 | B21: 14 | C21: 0 | D21: =B21+C21 -> 14 | E21: 参考（特別教育ではない） | F21: 労働安全衛生法第60条。安衛則40条の12時間以上に、安全衛生責任者分を加えた運用が一般的。要原典確認
A22: 【参考】有機溶剤業務従事者 労働衛生教育 | B22: 4.5 | C22: 0 | D22: =B22+C22 -> 4.5 | E22: 参考（特別教育ではない） | F22: 通達に基づく安全衛生教育。特別教育ではないため罰則の対象外。時間は実施機関により差がある
A25: ■ この表の読み方
A26: ・「学科」＝eラーニングで提供できる時間。この時間数が、制作する動画の尺を決める基準になります。
A27: ・「実技」＝オンラインで代替できません。受講者の所属事業者が自ら実施する前提です（フルハーネス等のWeb講座で一般的な提供形態）。
A28: ・法定時間は「以上」の定めです。動画の総再生時間だけでなく、章末テスト・演習時間を含めた総学習時間で満たす設計にします。
A30: ■ 出典と確認状況
A31: ・時間数は安全衛生特別教育規程（昭和47年労働省告示第92号）および各講習機関の公表カリキュラムに基づきます。
A32: ・複数の講習機関の公表値が一致することを確認していますが、契約前に規程の原典で科目ごとに確定させてください。
A33: ・「要原典確認」と記載した科目は、区分により時間が異なるため特に注意が必要です。

Sheet 03_教材制作費
A1: 教材制作費の試算
A2: 黄色のセルが入力欄です。A列の「制作対象」に 1 を入れた科目だけが集計されます。
A4: 単価設定（黄色セルを編集してください）
B5: 教材制作単価（学科1時間あたり） | C5: 250000 | E5: 構成台本の書き起こし、スライド制作、図解アニメーション、AI音声ナレーション、バーチャル講師映像、編集、書き出しまで。撮影は行いません。
B6: 専門家による監修費（1科目あたり） | C6: 350000 | E6: 労働安全衛生コンサルタント等の第三者監修。法定の科目・範囲・時間を満たしていることを、監修者名を明示して確認します。
B7: 理解度テスト制作（1科目あたり） | C7: 120000 | E7: 章末テストおよび修了確認テストの問題作成・解説文の作成。
B9: 参考：制作グレード別の単価目安（学科1時間あたり）
B10: グレード | C10: 単価/時間 | E10: 内容
B11: ライト | C11: 150000 | E11: スライド＋AI音声ナレーションのみ。図解は静止画。最も安価だが受講者の離脱率が上がりやすい。
B12: スタンダード（推奨） | C12: 250000 | E12: スライド＋図解アニメーション＋AI音声＋バーチャル講師。長時間の視聴に耐える構成。
B13: プレミアム | C13: 400000 | E13: 実写素材・3D図解・章ごとの演習を含む。差別化を最優先する場合。
A15: 科目別の試算（A列に 1 を入力した科目のみ集計されます）
A16: 制作対象 (1で選択) | B16: 業務の名称 | C16: 学科 (時間) | D16: 実技 (時間) | E16: 教材制作費 | F16: 監修費 | G16: テスト制作費 | H16: 科目 小計
A17: 1 | B17: =02_科目マスタ!A5 -> 足場の組立て等の業務 | C17: =02_科目マスタ!B5 -> 6 | D17: =02_科目マスタ!C5 -> 0 | E17: =IF($A17=1,$C17*$C$5,0) -> 1500000 | F17: =IF($A17=1,$C$6,0) -> 350000 | G17: =IF($A17=1,$C$7,0) -> 120000 | H17: =SUM(E17:G17) -> 1970000
A18: 0 | B18: =02_科目マスタ!A6 -> 粉じん作業に係る業務 | C18: =02_科目マスタ!B6 -> 4.5 | D18: =02_科目マスタ!C6 -> 0 | E18: =IF($A18=1,$C18*$C$5,0) -> 0 | F18: =IF($A18=1,$C$6,0) -> 0 | G18: =IF($A18=1,$C$7,0) -> 0 | H18: =SUM(E18:G18) -> 0
A19: 0 | B19: =02_科目マスタ!A7 -> 石綿等が使用されている建築物等の解体等の業務 | C19: =02_科目マスタ!B7 -> 4.5 | D19: =02_科目マスタ!C7 -> 0 | E19: =IF($A19=1,$C19*$C$5,0) -> 0 | F19: =IF($A19=1,$C$6,0) -> 0 | G19: =IF($A19=1,$C$7,0) -> 0 | H19: =SUM(E19:G19) -> 0
A20: 0 | B20: =02_科目マスタ!A8 -> 酸素欠乏・硫化水素危険作業（第2種） | C20: =02_科目マスタ!B8 -> 5.5 | D20: =02_科目マスタ!C8 -> 0 | E20: =IF($A20=1,$C20*$C$5,0) -> 0 | F20: =IF($A20=1,$C$6,0) -> 0 | G20: =IF($A20=1,$C$7,0) -> 0 | H20: =SUM(E20:G20) -> 0
A21: 1 | B21: =02_科目マスタ!A9 -> フルハーネス型墜落制止用器具を用いて行う作業 | C21: =02_科目マスタ!B9 -> 4.5 | D21: =02_科目マスタ!C9 -> 1.5 | E21: =IF($A21=1,$C21*$C$5,0) -> 1125000 | F21: =IF($A21=1,$C$6,0) -> 350000 | G21: =IF($A21=1,$C$7,0) -> 120000 | H21: =SUM(E21:G21) -> 1595000
A22: 1 | B22: =02_科目マスタ!A10 -> テールゲートリフターの操作の業務 | C22: =02_科目マスタ!B10 -> 4 | D22: =02_科目マスタ!C10 -> 2 | E22: =IF($A22=1,$C22*$C$5,0) -> 1000000 | F22: =IF($A22=1,$C$6,0) -> 350000 | G22: =IF($A22=1,$C$7,0) -> 120000 | H22: =SUM(E22:G22) -> 1470000
A23: 0 | B23: =02_科目マスタ!A11 -> 自由研削といしの取替え等の業務 | C23: =02_科目マスタ!B11 -> 4 | D23: =02_科目マスタ!C11 -> 3 | E23: =IF($A23=1,$C23*$C$5,0) -> 0 | F23: =IF($A23=1,$C$6,0) -> 0 | G23: =IF($A23=1,$C$7,0) -> 0 | H23: =SUM(E23:G23) -> 0
A24: 0 | B24: =02_科目マスタ!A12 -> 低圧電気取扱業務（開閉器の操作のみ） | C24: =02_科目マスタ!B12 -> 7 | D24: =02_科目マスタ!C12 -> 1 | E24: =IF($A24=1,$C24*$C$5,0) -> 0 | F24: =IF($A24=1,$C$6,0) -> 0 | G24: =IF($A24=1,$C$7,0) -> 0 | H24: =SUM(E24:G24) -> 0
A25: 0 | B25: =02_科目マスタ!A13 -> 低圧電気取扱業務（充電電路の敷設等） | C25: =02_科目マスタ!B13 -> 7 | D25: =02_科目マスタ!C13 -> 7 | E25: =IF($A25=1,$C25*$C$5,0) -> 0 | F25: =IF($A25=1,$C$6,0) -> 0 | G25: =IF($A25=1,$C$7,0) -> 0 | H25: =SUM(E25:G25) -> 0
A26: 0 | B26: =02_科目マスタ!A14 -> 高所作業車の運転（作業床の高さ10m未満） | C26: =02_科目マスタ!B14 -> 6 | D26: =02_科目マスタ!C14 -> 3 | E26: =IF($A26=1,$C26*$C$5,0) -> 0 | F26: =IF($A26=1,$C$6,0) -> 0 | G26: =IF($A26=1,$C$7,0) -> 0 | H26: =SUM(E26:G26) -> 0
A27: 0 | B27: =02_科目マスタ!A15 -> 玉掛けの業務（つり上げ荷重1トン未満） | C27: =02_科目マスタ!B15 -> 5 | D27: =02_科目マスタ!C15 -> 4 | E27: =IF($A27=1,$C27*$C$5,0) -> 0 | F27: =IF($A27=1,$C$6,0) -> 0 | G27: =IF($A27=1,$C$7,0) -> 0 | H27: =SUM(E27:G27) -> 0
A28: 0 | B28: =02_科目マスタ!A16 -> 小型車両系建設機械の運転（機体重量3トン未満） | C28: =02_科目マスタ!B16 -> 7 | D28: =02_科目マスタ!C16 -> 6 | E28: =IF($A28=1,$C28*$C$5,0) -> 0 | F28: =IF($A28=1,$C$6,0) -> 0 | G28: =IF($A28=1,$C$7,0) -> 0 | H28: =SUM(E28:G28) -> 0
... A30: 0 | B30: =02_科目マスタ!A18 -> アーク溶接等の業務 | C30: =02_科目マスタ!B18 -> 11 | D30: =02_科目マスタ!C18 -> 10 | E30: =IF($A30=1,$C30*$C$5,0) -> 0 | F30: =IF($A30=1,$C$6,0) -> 0 | G30: =IF($A30=1,$C$7,0) -> 0 | H30: =SUM(E30:G30) -> 0
A31: =SUM(A17:A30) -> 3 | B31: 合計（選択した科目数・時間・費用） | C31: =SUMPRODUCT($A17:$A30,$C17:$C30) -> 14.5 | E31: =SUM(E17:E30) -> 3625000 | F31: =SUM(F17:F30) -> 1050000 | G31: =SUM(G17:G30) -> 360000 | H31: =SUM(H17:H30) -> 5035000
A33: ■ 教材制作の進め方（撮影は行いません）
A34: 1. 法定の科目・範囲・時間を規程の原典から書き出し、章立てと各章の尺を設計します（ここで法定時間の充足を担保します）。
A35: 2. 構成台本を一から書き起こします。他社の講義映像や市販冊子をそのまま使うことは著作権法上できません。
A36: 3. スライド・図解を制作し、AI音声ナレーションとバーチャル講師映像を合成します。
A37: 4. 章末テストと修了確認テストを作成します。
A38: 5. 第三者の専門家が監修し、法定の科目・範囲・時間を満たしていることを監修者名を明示して確認します。
A40: ■ 2科目目以降について
A41: ・章立てのテンプレート、スライドのデザイン、動画の書き出し設定は1科目目で確立するため、2科目目以降は制作単価を抑えられます。
A42: ・目安として、2科目目以降は上表の8割程度を想定してください（監修費は科目ごとに必要です）。

Sheet 04_システム費用
A1: 配信システムの概算費用
A2: 実技会場の予約機能が不要になったため、前回ご提示分より構成を絞っています。
A4: 区分 | B4: 機能 | C4: 概算(下限) | D4: 概算(上限) | E4: 内容
A5: フェーズ1 | B5: 要件定義・基本設計 | C5: 400000 | D5: 700000 | E5: 業務フローの確定、画面設計、利用規約・特定商取引法表記・個人情報の取扱い方針の整備支援
A6: フェーズ1 | B6: 受講者ポータル | C6: 500000 | D6: 800000 | E6: アカウント登録、マイページ、受講状況の表示、スマートフォン対応
A7: フェーズ1 | B7: 本人確認・顔照合 | C7: 450000 | D7: 800000 | E7: 本人確認書類のアップロード、顔写真の登録、受講中のランダム自撮り撮影と照合、運営による承認フロー
A8: フェーズ1 | B8: 動画配信・視聴ログ | C8: 400000 | D8: 700000 | E8: 学科動画の配信、スキップ・早送りの禁止、視聴時間の秒単位記録（法定時間の充足を証明）
A9: フェーズ1 | B9: テスト・自動採点 | C9: 250000 | D9: 450000 | E9: 章末テスト（不合格なら次章に進めない制御）、修了確認テスト、自動採点
A10: フェーズ1 | B10: 修了証の発行 | C10: 200000 | D10: 350000 | E10: PDF修了証の自動発行、再ダウンロード、発行履歴の管理
A11: フェーズ2 | B11: 企業管理ポータル | C11: 400000 | D11: 700000 | E11: 発注企業のご担当者向け。従業員の一括申込、受講進捗の確認、修了者一覧のCSV出力
A12: フェーズ2 | B12: 決済（カード・請求書） | C12: 250000 | D12: 450000 | E12: クレジットカード決済、請求書払い、領収書の発行
A13: フェーズ2 | B13: 運営管理画面の拡張 | C13: 350000 | D13: 600000 | E13: 本人確認の承認キュー、顔照合アラート、受講ログの照会、売上・入金の管理
A14: フェーズ2 | B14: 記録保存・CSV出力 | C14: 200000 | D14: 350000 | E14: 労働安全衛生規則第38条に対応した3年以上の自動保存、一括出力
B15: フェーズ1 小計（まずここから始めます） | C15: =SUM(C5:C10) -> 2200000 | D15: =SUM(D5:D10) -> 3800000
B16: フェーズ2 小計（運用開始後に追加） | C16: =SUM(C11:C14) -> 1200000 | D16: =SUM(D11:D14) -> 2100000
B17: システム初期費用 合計 | C17: =C15+C16 -> 3400000 | D17: =D15+D16 -> 5900000
A19: 月額運用費
B20: 項目 | C20: 月額(下限) | D20: 月額(上限) | E20: 内容
B21: サーバー・インフラ | C21: 20000 | D21: 40000 | E21: クラウド利用料。受講者数の増加に応じて変動します
B22: 保守・障害対応 | C22: 30000 | D22: 50000 | E22: 監視、障害対応、軽微な改修
B23: 本人確認API（従量） | C23: 0 | D23: 0 | E23: 1件あたり100〜200円程度。受講申込者数に比例します
B24: 動画配信（従量） | C24: 0 | D24: 0 | E24: 視聴時間に比例。学科が長い科目ほど増えます
B25: 月額 固定費 合計（従量分を除く） | C25: =SUM(C21:C24) -> 50000 | D25: =SUM(D21:D24) -> 90000
A27: ■ 前回ご提示分からの変更点
A28: ・実技会場の予約機能、出欠管理機能を削除しました（実技は受講者の所属事業者が実施するため）。
A29: ・学科のみの提供に絞ったことで、フェーズ1の範囲が明確になり、着手しやすい構成になっています。

Sheet 05_前提・責任分界
A1: 前提条件と、責任の分担範囲
A2: ご契約前に、必ずこの内容についてご合意ください。
B4: ■ 1. 保証する範囲と、保証しない範囲
B5: ○ 弊社が保証すること
B6: ・教材が、安全衛生特別教育規程が定める科目・範囲・時間を満たしていること。
B7: ・その確認を、労働安全衛生の専門家（監修者）が、氏名と資格を明示したうえで行うこと。
B8: ・受講の記録（受講日時、視聴時間、本人確認の結果、テストの得点）を、証明可能な形で保存・出力できること。
B10: × 弊社が保証できないこと
B11: ・受講者の所属事業者が負う、労働安全衛生法第59条第3項の特別教育の実施義務が果たされたこと。
B12: この義務は法律上、受講者を雇用する事業者に課されるものであり、教材の提供者が代わりに負うことはできません。
B13: ・受講者が業務に従事した際に労働災害が発生しないこと。
B14: ・監督署その他の行政機関が、個別の事案において本教材の内容を適法と判断すること。
B16: ■ 2. 教材内容の監修について
B17: ・教材の法令適合性を確認できる専門家（労働安全衛生コンサルタント等）は、弊社が手配し、費用に含めてご提示します。
... B45: ・各科目の時間数は、上記規程および複数の講習機関が公表するカリキュラムで相互に確認しています。
