Workbook

Sheet 01_見積書
B2: 御 見 積 書
B4: 見積番号 | C4: SP-2026-0003
B5: 発行日 | C5: 2026年9月13日
B6: 有効期限 | C6: 発行日より30日間
B8: 株式会社聖建 御中 | E8: 株式会社スペリオル
B9: 〒475-0805 愛知県半田市浜田町1丁目7番地 | E9: 〒464-0075 名古屋市千種区内山3-18-10
E10: TEL 052-745-6607
E11: 登録番号 T9180001048541
E12: 担当 藤原
B14: 下記のとおりお見積り申し上げます。
B16: 件名 | C16: 建設業 特別教育 eラーニング配信システム 構築 および 教材制作（6科目）一式
B17: 御見積金額 | C17: ='03_見積明細'!F28
C18: ="消費税 ¥"&TEXT('03_見積明細'!F29,"#,##0")&" ／ 税込 ¥"&TEXT('03_見積明細'!F30,"#,##0")
B20: 納期 | C20: システム：ご発注後 約4か月 ／ 教材：第1次3科目 約4か月、第2次3科目 約7か月
B21: 納入場所 | C21: 貴社ご指定のサーバー環境
B22: 検収条件 | C22: 納品後14日以内に貴社にて検収。期間内にご連絡なき場合は検収完了とみなします。
B23: 支払条件 | C23: ご発注時に全額を一括でお支払いください。
B25: 内訳
B26: 区分 | C26: 内容 | E26: 数量 | F26: 金額（税抜）
B27: システム開発 | C27: 配信基盤・視聴整合性・本人確認・修了証発行・決済 | E27: 一式 | F27: ='03_見積明細'!F21
B28: 教材制作 | C28: 特別教育 学科教材 6科目 | E28: ='04_教材科目'!$A$17 | F28: ='04_教材科目'!$F$17
B29: 小計 | C29: （税抜） | F29: ='03_見積明細'!F26
B30: 値引 | C30: 貴社特別値引き | F30: ='03_見積明細'!F27
B31: 差引小計 | C31: （税抜） | F31: ='03_見積明細'!F28
B32: 消費税 | F32: ='03_見積明細'!F29
B33: 合計 | C33: （税込） | F33: ='03_見積明細'!F30
B35: ■ 別途ご負担いただく費用（いずれも税抜）
B36: ・月額 保守・運用サービス 60,000円 ＋ 法令改正監視・通知サービス 20,000円 合計 80,000円／月
B37: ・サーバー利用料 月額 20,000円程度（受講者数により変動）。貴社名義でのご契約を推奨します
B38: ・法令改正にともなう教材の改訂 1科目 300,000円（都度発注）

Sheet 02_増減内訳
A1: 前回お見積りからの増減内訳
A2: 2026年9月8日付 SP-2026-0001（税抜 8,000,000円）から、今回のお見積りに至るまでの内訳です。
B4: 項目 | C4: 増減 | D4: 人日 | E4: 理由・内容
B5: 前回お見積り（2026年9月8日） | C5: 8000000 | D5: 100 | E5: 教材10科目＋システム100人日
A6: ① | B6: 教材を10科目から6科目へ | C6: -1200000 | E6: 低圧電気、第2種酸欠、高所作業車、玉掛けの4科目を第2次発注へ。1科目300,000円×4科目
A7: ② | B7: 決済機能（ゼウス連携）の追加 | C7: 500000 | D7: 10 | E7: 株式会社ゼウスのAPI型決済を組み込み。申込から入金確認、受講開始までを自動化。今回の新規ご要望
A8: ③ | B8: 受講中のランダム顔照合を除外 | C8: -350000 | D8: -7 | E8: 受講の途中で予告なく撮影する機能を今回の範囲から外します。登録時の本人確認と受講開始時の照合は維持
A9: ④ | B9: 全額一括前払いによる調整 | C9: -350000 | E9: ご発注時に全額をお支払いいただく条件に対する調整。分割回収に比べ資金負担と与信リスクが下がるため
B10: 今回のお見積り（税抜） | C10: =C5+SUM(C6:C9) | D10: ='03_見積明細'!D21 | E10: 教材6科目＋システム103人日
B11: （検算）見積明細の小計＋調整額 | C11: ='03_見積明細'!F28
B13: 増減の内訳（金額の動き）
B14: 減額の要因
B15: 教材 4科目の削減 | C15: ▲1,200,000
B16: 受講中ランダム照合の除外 | C16: ▲350,000
B17: 全額一括前払いによる調整 | C17: ▲350,000
B18: 小計 | C18: ▲1,900,000
B20: 増額の要因
B21: 決済機能（ゼウス連携）の追加 | C21: ＋500,000
B22: 小計 | C22: ＋500,000
B24: 差引 | C24: ▲1,400,000 | E24: 8,000,000 − 1,400,000 ＝ 6,600,000
B26: ■ このシートは社内資料です（先方には提出しません）
B27: 提出するのは 01_見積書 ／ 06_注文書 ／ 07_前提条件 の3点のみです。
B28: 先方向けには「前回からの変更は受講中のランダム顔照合を外すことだけ」と説明し、
B29: 下の④は見積書・注文書の上では「貴社特別値引き（特別値引き）」と表示しています。
B31: ■ この表の使い方（社内の根拠整理）
B32: 単純な値引きではなく、次の3つの対価として金額が下がっていることを社内で説明できます。
B33: ① 納品する教材が4科目減ること（成果物の減少）
B34: ② 受講中のランダム照合を実装しないこと（機能の減少）
B35: ③ 全額を前払いいただくこと（支払条件の対価）
B37: 一方で、決済機能（ゼウス連携）は新しいご要望のため増額しています。
B38: 減る理由と増える理由の両方を示すことで、価格の根拠が明確になります。
B40: ■ 月額費用の変更
... B45: 合計 80,000円／月（サーバー費を除く・税抜）

Sheet 03_見積明細
A1: 見積明細
A2: 黄色のセルが編集箇所です。人日単価と各項目の人日を変えると、見積書・増減内訳・注文書まで自動で再計算されます。
A4: 人日単価 | C4: 50000 | D4: 円／人日
A6: 区分 | B6: 項目 | C6: 内容 | D6: 数量 | E6: 単価 | F6: 金額
A7: 1. システム開発
A8: システム | B8: 要件定義・基本設計 | C8: 業務フローの確定、データモデル設計、API設計、画面設計、利用規約・特定商取引法表記・個人情報の取扱い方針の整備支援 | D8: 8 | E8: =$C$4 | F8: =D8*E8
A9: システム | B9: AWS本番環境の構築 | C9: VPC、EC2、RDS PostgreSQL（Multi-AZ・自動バックアップ・PITR）、ElastiCache、ALB、S3、CloudFront、CloudWatch の構築とCI/CD | D9: 7 | E9: =$C$4 | F9: =D9*E9
A10: システム | B10: 動画配信基盤 | C10: HLS変換（FFmpeg）、短寿命の署名付きマニフェスト配信、章単位の受講制御、MP4直リンクの排除 | D10: 12 | E10: =$C$4 | F10: =D10*E10
A11: システム | B11: 視聴整合性・実視聴時間の集計 | C11: heartbeatの受信と検証、未視聴位置へのシーク制限、倍速検知、可視状態の判定、サーバー側での検証済み秒数の集計、異常検知 | D11: 15 | E11: =$C$4 | F11: =D11*E11
A12: システム | B12: 本人確認（登録時） | C12: その場撮影UI（getUserMedia）、ライブネス判定、本人確認書類との突合、顔の1:1照合、運営の審査画面 | D12: 11 | E12: =$C$4 | F12: =D12*E12
A13: システム | B13: PC↔スマートフォン引き継ぎ | C13: QRコードとワンタイムURLによる撮影工程の引き継ぎ | D13: 3 | E13: =$C$4 | F13: =D13*E13
A14: システム | B14: 顔照合（受講開始時のみ） | C14: 各章の再生開始時に1:1照合を実施。受講中のランダム照合は今回の範囲外とします | D14: 4 | E14: =$C$4 | F14: =D14*E14
A15: システム | B15: 確認問題・自動採点 | C15: 章末問題、修了確認テスト、出題のランダム化、不合格後の再受講制御 | D15: 7 | E15: =$C$4 | F15: =D15*E15
A16: システム | B16: 修了判定・修了証の発行 | C16: サーバー側での修了条件の再検証、修了記録の作成、修了証PDFの発行・再発行・ダウンロード | D16: 7 | E16: =$C$4 | F16: =D16*E16
A17: システム | B17: 決済機能（ゼウス連携） | C17: 株式会社ゼウスのデータ転送（API）型による決済組み込み。申込から入金確認、受講開始までの自動化。領収書の発行 | D17: 10 | E17: =$C$4 | F17: =D17*E17
A18: システム | B18: 受講者ポータル | C18: 申込、マイページ、受講画面、進捗表示、スマートフォン対応 | D18: 9 | E18: =$C$4 | F18: =D18*E18
A19: システム | B19: 運営管理画面（基本機能） | C19: 本人確認の承認キュー、受講状況の一覧、受講ログの照会、修了証の発行管理 | D19: 4 | E19: =$C$4 | F19: =D19*E19
A20: システム | B20: 結合テスト・E2E・受入支援 | C20: 必須E2Eシナリオの実施、受入条件の確認、リリース判定資料の作成 | D20: 6 | E20: =$C$4 | F20: =D20*E20
B21: システム開発 小計 | D21: =SUM(D8:D20) | F21: =SUM(F8:F20)
A23: 2. eラーニング教材の制作
A24: 教材 | B24: 特別教育 学科教材の制作 | C24: ="6科目・学科"&TEXT('04_教材科目'!$D$17,"0.0")&"時間分。構成台本の書き起こし、スライド、図解、ナレーション、バーチャル講師映像、章末問題・修了確認テストの作成" | D24: ='04_教材科目'!$A$17 | E24: ='04_教材科目'!$D$4 | F24: ='04_教材科目'!$F$17
B26: 小計（税抜） | D26: =D21 | F26: =F21+F24
B27: 全額一括前払いによる調整 | C27: ご発注時に全額をお支払いいただく条件に対する調整額です | F27: -350000
B28: 差引 小計（税抜） | F28: =F26+F27
B29: 消費税 | C29: 税率 | D29: 0.1 | F29: =ROUND(F28*D29,0)
B30: 合計（税込） | F30: =F28+F29
A32: ■ 今回の範囲から外したもの（第2次発注のご相談）
A33: ・受講中のランダム顔照合（受講の途中で予告なく撮影し、本人が継続して受講しているかを確認する機能）
A34: ・企業管理ポータル（従業員の一括申込、進捗確認、修了者一覧のCSV出力）
A35: ・運営管理画面の拡張（監査レポート出力、組織管理、売上・入金管理）
A36: ・受講画面からの質疑応答機能（当面はメールで対応）
A37: ・修了証の真正性検証ページ（QRコード）
A38: ・教材 4科目（低圧電気、第2種酸欠、高所作業車、玉掛け）
A40: ■ 本見積に含まれないもの（別途）
A41: ・月額の保守・運用サービスおよび法令改正監視・通知サービス（シート05）
A42: ・AWSの利用料（聖建様のご負担）、株式会社ゼウスとのご契約（初期費用無料・月額3,000円・決済手数料）
A43: ・法令改正にともなう教材の改訂（1科目300,000円・都度発注）

Sheet 04_教材科目
A1: eラーニング教材 制作科目一覧（6科目）
A2: A列に 1 を入れた科目が制作対象になります。10科目から6科目へ絞り込んだ状態です。
B4: 制作単価（1科目あたり） | D4: 300000 | E4: 円／科目
A6: 制作 (1で選択) | B6: 優先 順位 | C6: 特別教育の名称 | D6: 学科 (時間) | E6: 選定・除外の理由 | F6: 制作費
A7: 1 | B7: 1 | C7: フルハーネス型墜落制止用器具 | D7: 4.5 | E7: 対象職種が最も広く、初期商品群の中核 | F7: =IF(A7=1,$D$4,0)
A8: 1 | B8: 2 | C8: 足場の組立て・解体・変更 | D8: 6 | E8: 実技の定めがなく、学科のみで修了まで完結する | F8: =IF(A8=1,$D$4,0)
A9: 1 | B9: 3 | C9: 自由研削用といし | D9: 4 | E9: 幅広い工種で利用され、学科時間もコンパクト | F9: =IF(A9=1,$D$4,0)
A10: 0 | B10: 4 | C10: 低圧電気取扱業務 | D10: 7 | E10: 学科7時間と最長級。制作負担が大きく第2次へ | F10: =IF(A10=1,$D$4,0)
A11: 1 | B11: 5 | C11: アーク溶接等 | D11: 11 | E11: 既存の制作資産を活用できるため優先 | F11: =IF(A11=1,$D$4,0)
A12: 1 | B12: 6 | C12: 石綿使用建築物等の解体・破砕等 | D12: 4.5 | E12: 実技なし。解体・改修の需要が継続的にある | F12: =IF(A12=1,$D$4,0)
A13: 1 | B13: 7 | C13: 特定粉じん作業 | D13: 4.5 | E13: 実技なし。建設現場の有害業務として汎用性が高い | F13: =IF(A13=1,$D$4,0)
A14: 0 | B14: 8 | C14: 第2種酸素欠乏危険作業 | D14: 5.5 | E14: 対象職種が設備・土木に限られるため第2次へ | F14: =IF(A14=1,$D$4,0)
A15: 0 | B15: 9 | C15: 高所作業車（10m未満） | D15: 6 | E15: 実技3時間を伴い、対象が限定的なため第2次へ | F15: =IF(A15=1,$D$4,0)
A16: 0 | B16: 10 | C16: 玉掛け（1t未満） | D16: 5 | E16: 実技4時間を伴い、対象が限定的なため第2次へ | F16: =IF(A16=1,$D$4,0)
A17: =SUM(A7:A16) | C17: 制作対象 合計 | D17: =SUMPRODUCT($A7:$A16,$D7:$D16) | F17: =SUM(F7:F16)
A19: ■ 選定の考え方
A20: ・実技の定めがない科目（足場・石綿・特定粉じん）を優先し、最短で販売を開始できるようにしています。
A21: ・アーク溶接等は既存の制作資産があるため、優先して商品化します。
A22: ・除外した4科目は、学科時間が長いか対象職種が限定的なものです。第2次発注でのご検討をお願いします。
A23: ・A列の 1 と 0 を入れ替えれば、対象科目を自由に変更できます（見積金額も自動で追随します）。

Sheet 05_月額・別途費用
A1: 月額費用と別途費用
A2: 初期費用（シート01）とは別に、下記が発生します。金額はすべて税抜です。
A4: 区分 | B4: 項目 | C4: 月額／単価 | D4: 内容
A5: 弊社へ お支払い | B5: 保守・運用サービス | C5: 60000 | D5: システムの死活監視とエラー監視、障害対応、軽微な改修、受講者からの問い合わせ一次対応、月次レポート。受講中のランダム照合を実装しないため、照合結果の目視確認が不要となり、前回の80,000円から減額しています
B6: 法令改正監視・通知サービス | C6: 20000 | D6: 月2回（月初・月中）、官報・厚生労働省の通達・パブリックコメントを確認。対象6科目に影響しうる改正を検知したら、聖建様と弊社の双方へ自動でメール通知。月次で「該当なし」も含めて報告
B7: 月額 小計（サーバー費を除く） | C7: =SUM(C5:C6) | D7: 聖建様のご指定額です
A9: お客様 ご負担 | B9: AWS 利用料（構成B・推奨） | C9: 22800 | D9: EC2、RDS PostgreSQL（Multi-AZ・自動バックアップ・PITR）、ElastiCache、ALB、S3、CloudFront、CloudWatch。聖建様名義でのご契約を推奨します
B10: 従量課金（顔照合・配信ほか） | C10: 実費 | D10: 顔照合API、ライブネス判定、CDN転送、メール送信。受講者100名／月で約600円（AWS利用料に含まれます）
B11: 株式会社ゼウス（決済代行） | C11: 3000 | D11: 初期費用は無料。月額3,000円。クレジットカード決済手数料は最大3.5%（売上に応じて発生）。聖建様が直接ご契約いただきます
A13: 都度 発注 | B13: 教材の改訂（法令改正対応） | C13: ='04_教材科目'!D4 | D13: 1科目あたり。新規制作と同額です。台本の修正、該当部分の動画の再生成と差し替え、教材の版の更新を含みます
B14: 教材の追加制作（第2次） | C14: ='04_教材科目'!D4 | D14: 低圧電気、第2種酸欠、高所作業車、玉掛けの4科目。1科目あたり300,000円
A16: 参考：月額の合計（聖建様のご負担総額）
B17: 弊社サービス ＋ AWS ＋ ゼウス月額 | C17: ='05_月額・別途費用'!C7+C9+C11 | D17: 税抜。決済手数料は売上に応じて別途発生します
A19: ■ 月額80,000円の根拠
A20: 聖建様のご指定額（サーバー費を除く月額80,000円）にあわせ、内訳を次のとおり組みました。
A21: ・保守・運用サービス 60,000円 … 受講中のランダム照合を実装しないため、照合結果の
A22: 目視確認という運用作業がなくなります。その分を減額しています。
A23: ・法令改正監視・通知サービス 20,000円 … 前回から変更ありません。
A25: ■ ゼウスについて
A26: ・株式会社ゼウス（1994年設立・国内の決済代行事業者）との契約は聖建様が直接行っていただきます。
A27: ・初期費用は無料、月額3,000円、クレジットカード決済手数料は最大3.5%です（2026年9月時点）。
A28: ・接続方式はデータ転送（API）型を想定しています。申込から入金確認、受講開始までを自動化します。
A29: ・最新の料金と条件は、ご契約前にゼウス社へ直接ご確認ください。

Sheet 06_注文書
B2: 注 文 書
B4: 注文番号 | C4: SP-2026-0003
B5: 発行日 | C5: 年 月 日
B7: 株式会社スペリオル 御中 | E7: 発注者
B8: 〒464-0075 名古屋市千種区内山3-18-10 | E8: 株式会社聖建
B9: TEL 052-745-6607 ／ 登録番号 T9180001048541 | E9: 〒475-0805 愛知県半田市浜田町1丁目7番地
E10: TEL 0569-84-9669
E11: ご担当 印
B13: 下記のとおり注文いたします。
B15: 件名 | C15: 建設業 特別教育 eラーニング配信システム 構築 および 教材制作（6科目）一式
B16: 根拠見積 | C16: ='01_見積書'!C4&"（"&'01_見積書'!C5&" 発行）"
B18: 区分 | C18: 内容 | D18: 数量 | F18: 金額（税抜）
B19: システム開発 | C19: 配信基盤・視聴整合性・本人確認・修了証発行・決済 | D19: 一式 | F19: ='03_見積明細'!F21
B20: 教材制作 | C20: 特別教育 学科教材 6科目 | D20: ='04_教材科目'!$A$17 | F20: ='04_教材科目'!$F$17
B21: 小計（税抜） | F21: =SUM(F19:F20)
B22: 特別値引き | F22: ='03_見積明細'!F27
B23: 消費税 | D23: ='03_見積明細'!D29 | F23: =ROUND((F21+F22)*D23,0)
B24: ご注文金額（税込） | F24: =F21+F22+F23
B26: 納期 | C26: システム：ご発注後 約4か月 ／ 教材：第1次3科目 約4か月、第2次3科目 約7か月
B27: 納入場所 | C27: 貴社ご指定のサーバー環境
B28: 検収条件 | C28: 納品後14日以内に検収。期間内にご連絡なき場合は検収完了とみなします。
B29: 支払条件 | C29: 本注文書の発行時に、上記ご注文金額の全額を一括でお支払いいたします。
B31: ■ 別途ご負担いただく費用（いずれも税抜）
B32: ・月額 保守・運用サービス 60,000円 ＋ 法令改正監視・通知サービス 20,000円 合計 80,000円／月
B33: ・サーバー利用料 月額 20,000円程度（受講者数により変動）。貴社名義でのご契約を推奨します
B34: ・法令改正にともなう教材の改訂 1科目 300,000円（都度発注）

Sheet 07_前提条件
B1: 見積の前提条件
B3: ■ 1. 本見積に含まれるもの
B4: システム開発 | C4: 配信基盤、視聴整合性、登録時の本人確認、受講開始時の顔照合、確認問題、修了判定、修了証の発行、決済機能、受講者ポータル、運営管理画面の基本機能。
B5: 教材制作 | C5: 特別教育 学科教材 6科目。構成台本、スライド、図解、ナレーション、章末問題・修了確認。
B6: 修了証 | C6: 修了証PDFの自動発行、再発行、受講者によるダウンロード。記載項目は受講者氏名、科目、法定学科時間、有効視聴時間、テスト得点、講師名、発行者、証明書番号。
B7: サーバー環境の構築 | C7: 本番運用に耐える構成で構築します。データベースは冗長化し、日次のバックアップを取得します。
B9: ■ 2. 本見積に含まれないもの（別途）
B10: 受講中のランダム顔照合 | C10: 受講の途中で予告なく撮影し、本人が継続して受講しているかを確認する機能は含みません。 登録時の本人確認と受講開始時の顔照合は実装します。
B11: 月額サービス | C11: 保守・運用サービス 60,000円／月、法令改正監視・通知サービス 20,000円／月。合計80,000円／月（税抜）。
B12: サーバー利用料 | C12: 貴社のご負担とします。月額20,000円程度（税抜）。貴社名義でのご契約をお願いします。
B13: 教材の改訂・追加 | C13: 1科目300,000円（都度発注）。
B14: 教材の監修 | C14: 内容の監修は貴社の社内有資格者が担われる前提です。
B16: ■ 3. 責任の分担
B17: 弊社が保証すること | C17: 教材が安全衛生特別教育規程の定める科目・範囲・時間を満たすこと（監修者名を明示）。受講記録を証明可能な形で保存・出力できること。
B18: 弊社が保証しないこと | C18: 受講者の所属事業者が負う労働安全衛生法第59条第3項の実施義務が果たされたこと。労働災害が発生しないこと。行政機関が個別の事案において本教材を適法と判断すること。
B19: 法令改正への対応 | C19: 弊社は官報・通達を監視し、該当しうる改正を自動でメール通知します。その改正が教材のどこに影響するかの判断は、貴社の監修者が行うものとします。
B21: ■ 4. 金額の前提
B22: 教材制作単価 | C22: 300,000円／科目。貴社ご指定の単価です。改訂・追加時も同額を適用します。
B23: 支払条件 | C23: ご発注時に全額を一括でお支払いいただくことを前提とした金額です。
B24: 有効期限 | C24: 発行日より30日間。
